{
  "players": {
    "384718982625886208": {
      "hash": "1596c3e5c9bd2cc1ef62d2456b02159934f2048abcd5c197107bc23c022653ddc6947588d59a0e7eb202d9de990854c9fad52f81341e77d35ec846219a369029",
      "attackable": false,
      "notag": true
    },
    "837815287897128990": {
      "hash": "04a06c7cdf52342dc1cc337cc9c9ea51aecfeea6e9f793547bbfc0eb128e419ef55e09f88c103b75740072f4bc64ef84b9f2061b71b6dfd4f0d65a20f85cfa93",
      "attackable": false,
      "notag": false
    }
  },
  "owners": {
    "1059269872011444354": {
      "hash": "b9ed6fcb2b83b27d55700500e1743cb907a6d4c8f59f4dac1be05288553830f7777c8441813247ae8e14aaca1a43765a942f240c48bd0efe3f9f1aa8dbbd08fe",
      "attackable": false,
      "notag": false
    }
  },
  "chattags": {
    "1596c3e5c9bd2cc1ef62d2456b02159934f2048abcd5c197107bc23c022653ddc6947588d59a0e7eb202d9de990854c9fad52f81341e77d35ec846219a369029": {
      "NameColor": {
        "r": 3,
        "g": 207,
        "b": 252
      },
      "Tags": [
        {
          "TagColor": {
            "r": 3,
            "g": 207,
            "b": 252
          },
          "TagText": "PRISM OWNER"
        }
      ]
    },
    "04a06c7cdf52342dc1cc337cc9c9ea51aecfeea6e9f793547bbfc0eb128e419ef55e09f88c103b75740072f4bc64ef84b9f2061b71b6dfd4f0d65a20f85cfa93": {
      "NameColor": {
        "r": 255,
        "g": 255,
        "b": 0
      },
      "Tags": [
        {
          "TagColor": {
            "r": 255,
            "g": 255,
            "b": 0
          },
          "TagText": "VAPE USER"
        }
      ]
    }
  },
  "specialusers": {
    "529155884643909643": {
      "NameColor": {
        "r": 70,
        "g": 70,
        "b": 255
      },
      "Tag": {
        "TagColor": {
          "r": 70,
          "g": 70,
          "b": 255
        },
        "TagText": "SYNAPSE OWNER"
      }
    },
    "582558971722727424": {
      "NameColor": {
        "r": 40,
        "g": 40,
        "b": 140
      },
      "Tag": {
        "TagColor": {
          "r": 40,
          "g": 40,
          "b": 140
        },
        "TagText": "SYNAPSE STAFF"
      }
    },
    "1030586129466003537": {
      "NameColor": {
        "r": 70,
        "g": 70,
        "b": 255
      },
      "Tag": {
        "TagColor": {
          "r": 70,
          "g": 70,
          "b": 255
        },
        "TagText": "SYNAPSE OWNER"
      }
    },
    "384718982625886208": {
      "NameColor": {
        "r": 3,
        "g": 207,
        "b": 252
      },
      "Tag": {
        "TagColor": {
          "r": 3,
          "g": 207,
          "b": 252
        },
        "TagText": "PRISM OWNER"
      }
    },
    "548146409065545730": {
      "NameColor": {
        "r": 0,
        "g": 255,
        "b": 0
      },
      "Tag": {
        "TagColor": {
          "r": 0,
          "g": 255,
          "b": 0
        },
        "TagText": "TYPEWRITER"
      }
    },
    "837815287897128990": {
      "NameColor": {
        "r": 255,
        "g": 255,
        "b": 0
      },
      "Tag": {
        "TagColor": {
          "r": 255,
          "g": 255,
          "b": 0
        },
        "TagText": "VAPE USER"
      }
    },
    "709094619161296939": {
      "NameColor": {
        "r": 174,
        "g": 255,
        "b": 53
      },
      "Tag": {
        "TagColor": {
          "r": 174,
          "g": 255,
          "b": 53
        },
        "TagText": "BALLER"
      }
    }
  }
}